hydrozincite-0.1.3.dist-info/METADATA
hydrozincite-0.1.3.dist-info/WHEEL
hydrozincite-0.1.3.dist-info/entry_points.txt
hydrozincite-0.1.3.dist-info/licenses/LICENSE
hydrozincite/__init__.py
hydrozincite/config/args.py
hydrozincite/config/config.py
hydrozincite/config/toml.py
hydrozincite/hook.py
hydrozincite/log/log.py
hydrozincite/main.py
hydrozincite/render.py
hydrozincite/repo.py
hydrozincite-0.1.3.dist-info/RECORD
