Metadata-Version: 2.1
Name: hydrozincite
Version: 0.1.3
Summary: Hydrozincite - Zn₅(CO₃)₂(OH)₆
Keywords: git static
Author-Email: HS-157 <hs-157@lett.re>
License: Copyright (c) 2020, HS-157
Project-URL: Repository, https://forge.dotslashplay.it/HS-157/Hydrozincite
Requires-Python: >=3.11
Requires-Dist: rich>=13.5.2
Requires-Dist: GitPython>=3.1.36
Requires-Dist: Jinja2>=3.1.2
